pout2prot/Analyzer.py
pout2prot/OccamsRazorPreprocessor.py
pout2prot/OutputWriter.py
pout2prot/Parser.py
pout2prot/ProteinGrouping.py
pout2prot/ProteinSubGrouping.py
pout2prot/main.py
pout2prot-1.3.0.dist-info/METADATA
pout2prot-1.3.0.dist-info/WHEEL
pout2prot-1.3.0.dist-info/entry_points.txt
pout2prot-1.3.0.dist-info/top_level.txt
pout2prot-1.3.0.dist-info/RECORD
