Metadata-Version: 2.1
Name: pout2prot
Version: 1.3.0
Summary: A script to perform protein grouping on pout-files (generated by Percolator).
Home-page: UNKNOWN
Author: Pieter Verschaffelt
Author-email: pieter.verschaffelt@ugent.be
License: UNKNOWN
Platform: UNKNOWN
